{"region":"Bretagne","code":"FRH0335288M035530","situationUpdate":"Pas de changement","name":"Bon Secours","insee":"35288","city":"Saint-Malo","ueDeclarationDate":"01/01/1995","type":"Eau côtière","lng":"-2.02943427197","lat":"48.64845392521","idSite":"000830","siteDetails":{"surveillance":true,"amenities":true,"animalsAllowed":false,"showers":false,"drinkingWater":true,"wheelchairAccess":true,"toilets":true,"lifeguard":true,"seasonStart":"2025-06-15T00:00:00.000Z","seasonEnd":"2025-09-15T00:00:00.000Z","lastWaterQuality":"Insuffisant","lastTestDate":"2025-09-01T00:00:00.000Z"},"score":5,"department":"Ille-et-Vilaine","slug":"bon-secours-saint-malo"}