{"region":"Occitanie","code":"FRJ1334154M034205","situationUpdate":"Pas de changement","name":"Carnon Palavas - la Roquille","insee":"34154","city":"Mauguio","ueDeclarationDate":"01/01/1991","type":"Eau côtière","lng":"3.970044456","lat":"43.54043183","idSite":"003205","siteDetails":{"surveillance":true,"amenities":true,"animalsAllowed":false,"showers":false,"drinkingWater":true,"wheelchairAccess":false,"toilets":true,"lifeguard":true,"seasonStart":"2025-07-01T00:00:00.000Z","seasonEnd":"2025-09-15T00:00:00.000Z","lastWaterQuality":"Excellent","lastTestDate":"2025-09-01T00:00:00.000Z"},"score":80,"images":[{"url":"https://upload.wikimedia.org/wikipedia/commons/8/8f/Boat_%28163442141%29.jpeg","thumbUrl":"https://upload.wikimedia.org/wikipedia/commons/thumb/8/8f/Boat_%28163442141%29.jpeg/960px-Boat_%28163442141%29.jpeg","title":"Boat (163442141).jpeg","description":"<div class=\"description\">\n500px provided description: Boat [#sky ,#landscape ,#sea ,#ocean ,#evening ,#france ,#purple ,#mediterranean ,#outlook ,#Boat]</div>","license":"CC BY 3.0","score":75},{"url":"https://upload.wikimedia.org/wikipedia/commons/6/6c/Carnon-Plage%2C_Mauguio%2C_France_%28Unsplash%29.jpg","thumbUrl":"https://upload.wikimedia.org/wikipedia/commons/thumb/6/6c/Carnon-Plage%2C_Mauguio%2C_France_%28Unsplash%29.jpg/960px-Carnon-Plage%2C_Mauguio%2C_France_%28Unsplash%29.jpg","title":"Carnon-Plage, Mauguio, France (Unsplash).jpg","description":"Carnon-Plage, Mauguio, France","license":"CC0","score":20}],"department":"Hérault","slug":"carnon-palavas-la-roquille-mauguio"}