{"region":"Grand Est","code":"FRF3357003D057005","situationUpdate":"Pas de changement","name":"Etang de la Forge","insee":"57003","city":"Abreschviller","ueDeclarationDate":"01/01/1992","type":"Lac","lng":"7.09266470618","lat":"48.63554572142","idSite":"001969","siteDetails":{"surveillance":true,"amenities":true,"animalsAllowed":false,"showers":true,"drinkingWater":true,"wheelchairAccess":false,"toilets":true,"lifeguard":true,"seasonStart":"2025-07-01T00:00:00.000Z","seasonEnd":"2025-08-31T00:00:00.000Z","lastWaterQuality":"Excellent","lastTestDate":"2025-09-01T00:00:00.000Z"},"score":85,"images":[],"department":"Moselle","slug":"etang-de-la-forge-abreschviller"}