{"region":"Auvergne-Rhône-Alpes","code":"FRK2874119D074090","situationUpdate":"Pas de changement","name":"Evian  Centre Nautique","insee":"74119","city":"Evian-les-Bains","ueDeclarationDate":"01/01/1991","type":"Lac","lng":"6.58118570185","lat":"46.40071424732","idSite":"003370","siteDetails":{"surveillance":true,"amenities":true,"animalsAllowed":false,"showers":true,"drinkingWater":true,"wheelchairAccess":true,"toilets":true,"lifeguard":true,"seasonStart":"2025-06-07T00:00:00.000Z","seasonEnd":"2025-08-31T00:00:00.000Z","lastWaterQuality":"Excellent","lastTestDate":"2025-09-01T00:00:00.000Z"},"score":100,"images":[],"department":"Haute-Savoie","slug":"evian-centre-nautique-evian-les-bains"}