{"region":"Normandie","code":"FRD1250481M050300","situationUpdate":"Pas de changement","name":"Face au Cd 306","insee":"50481","city":"Saint-Germain-sur-Ay","ueDeclarationDate":"01/01/1991","type":"Eau côtière","lng":"-1.64826304635","lat":"49.23096788346","idSite":"002180","siteDetails":{"surveillance":false,"amenities":false,"animalsAllowed":true,"showers":false,"drinkingWater":false,"wheelchairAccess":false,"toilets":false,"lifeguard":false,"seasonStart":"2025-06-15T00:00:00.000Z","seasonEnd":"2025-09-15T00:00:00.000Z","lastWaterQuality":"Bon","lastTestDate":"2025-09-01T00:00:00.000Z"},"score":10,"images":[],"department":"Manche","slug":"face-au-cd-306-saint-germain-sur-ay"}