{"region":"Corse","code":"FRM012A228M02A215","situationUpdate":"Pas de changement","name":"Isolella Nord","insee":"2A228","city":"Pietrosella","ueDeclarationDate":"01/01/1991","type":"Eau côtière","lng":"8.76115726405","lat":"41.84783870630","idSite":"001970","siteDetails":{"surveillance":false,"amenities":false,"animalsAllowed":true,"showers":false,"drinkingWater":false,"wheelchairAccess":false,"toilets":false,"lifeguard":false,"seasonStart":"2025-06-15T00:00:00.000Z","seasonEnd":"2025-09-19T00:00:00.000Z","lastWaterQuality":"Excellent","lastTestDate":"2025-09-01T00:00:00.000Z"},"score":20,"images":[{"url":"https://upload.wikimedia.org/wikipedia/commons/2/27/Tour_g%C3%A9noise_de_l%E2%80%99Isolella_16o8_%C3%A0_Pietrosella%2C_rive_sud_du_golfe_d%E2%80%99Ajaccio_En_Corse_du_sud.jpg","thumbUrl":"https://upload.wikimedia.org/wikipedia/commons/thumb/2/27/Tour_g%C3%A9noise_de_l%E2%80%99Isolella_16o8_%C3%A0_Pietrosella%2C_rive_sud_du_golfe_d%E2%80%99Ajaccio_En_Corse_du_sud.jpg/960px-Tour_g%C3%A9noise_de_l%E2%80%99Isolella_16o8_%C3%A0_Pietrosella%2C_rive_sud_du_golfe_d%E2%80%99Ajaccio_En_Corse_du_sud.jpg","title":"Tour génoise de l’Isolella 16o8 à Pietrosella, rive sud du golfe d’Ajaccio En Corse du sud.jpg","description":"Tour d'Isolella","license":"CC BY-SA 4.0","score":20}],"department":"Corse-du-Sud","slug":"isolella-nord-pietrosella"}