{"region":"Pays de la Loire","code":"FRG0585113M085045","situationUpdate":"Pas de changement","name":"Ker Chalon Droite","insee":"85113","city":"Ile-d'Yeu (L')","ueDeclarationDate":"01/01/1991","type":"Eau côtière","lng":"-2.33111929199","lat":"46.71991650459","idSite":"000919","siteDetails":{"surveillance":false,"amenities":true,"animalsAllowed":false,"showers":false,"drinkingWater":false,"wheelchairAccess":false,"toilets":false,"lifeguard":false,"seasonStart":"2025-06-15T00:00:00.000Z","seasonEnd":"2025-09-15T00:00:00.000Z","lastWaterQuality":"Excellent","lastTestDate":"2025-09-01T00:00:00.000Z"},"score":15,"images":[],"department":"Vendée","slug":"ker-chalon-droite-ile-d-yeu-l"}