{"region":"Auvergne-Rhône-Alpes","code":"FRK2207237D007455","situationUpdate":"Pas de changement","name":"L'Eyrieux au Lieu Dit le Pigeonnier","insee":"7237","city":"Saint-Fortunat-sur-Eyrieux","ueDeclarationDate":"01/01/1991","type":"Rivière","lng":"4.68208686877","lat":"44.82854566919","idSite":"002010","siteDetails":{"surveillance":false,"amenities":false,"animalsAllowed":true,"showers":false,"drinkingWater":false,"wheelchairAccess":false,"toilets":false,"lifeguard":false,"seasonStart":"2025-07-01T00:00:00.000Z","seasonEnd":"2025-08-31T00:00:00.000Z","lastWaterQuality":"Bon","lastTestDate":"2025-09-01T00:00:00.000Z"},"score":10,"images":[],"department":"Ardèche","slug":"l-eyrieux-au-lieu-dit-le-pigeonnier-saint-fortunat-sur-eyrieux","nearbySpots":[{"slug":"l-eyrieux-a-la-plage-de-la-theoule-ollieres-sur-eyrieux-les","name":"L'Eyrieux a la Plage de la Theoule","city":"Ollieres-sur-Eyrieux (Les)","department":"Ardèche","type":"Rivière","distanceKm":5.8,"score":20,"lastWaterQuality":"Bon","thumbUrl":"https://upload.wikimedia.org/wikipedia/commons/thumb/d/d0/Hierophis_viridiflavus_juvenile.JPG/960px-Hierophis_viridiflavus_juvenile.JPG"},{"slug":"le-lac-aux-ramiers-vernoux-en-vivarais","name":"Le Lac aux Ramiers","city":"Vernoux-en-Vivarais","department":"Ardèche","type":"Lac","distanceKm":7.3,"score":75,"lastWaterQuality":"Excellent"},{"slug":"la-glueyre-a-la-plage-de-fontugne-gluiras","name":"La Glueyre a la Plage de Fontugne","city":"Gluiras","department":"Ardèche","type":"Rivière","distanceKm":9.2,"score":-5,"lastWaterQuality":"Insuffisant"},{"slug":"le-mezayon-au-lieu-dit-la-neuve-lyas","name":"Le Mezayon au Lieu Dit la Neuve","city":"Lyas","department":"Ardèche","type":"Rivière","distanceKm":12.2,"score":0,"lastWaterQuality":"Insuffisant"},{"slug":"le-doux-au-lieu-dit-le-retourtour-lamastre","name":"Le Doux au Lieu Dit le Retourtour","city":"Lamastre","department":"Ardèche","type":"Rivière","distanceKm":20.2,"score":5,"lastWaterQuality":"Insuffisant"},{"slug":"l-eyrieux-a-la-plage-du-chambaud-cheylard-le","name":"L'Eyrieux a la Plage du Chambaud","city":"Cheylard (Le)","department":"Ardèche","type":"Rivière","distanceKm":22.8,"score":-10,"lastWaterQuality":"Insuffisamment de prélèvements"},{"slug":"le-doux-a-la-plage-des-salins-desaignes","name":"Le Doux a la Plage des Salins","city":"Desaignes","department":"Ardèche","type":"Rivière","distanceKm":23.1,"score":70,"lastWaterQuality":"Excellent"},{"slug":"le-doux-a-la-plage-de-labatie-labatie-d-andaure","name":"Le Doux a la Plage de Labatie","city":"Labatie-d'Andaure","department":"Ardèche","type":"Rivière","distanceKm":26.5,"score":80,"lastWaterQuality":"Excellent","thumbUrl":"https://upload.wikimedia.org/wikipedia/commons/thumb/5/5d/Labatie_d%27Andaure.JPG/960px-Labatie_d%27Andaure.JPG"}]}