{"region":"Pays de la Loire","code":"FRG0585234M085145","situationUpdate":"Pas de changement","name":"La Grande Plage","insee":"85234","city":"Saint-Jean-de-Monts","ueDeclarationDate":"01/01/1991","type":"Eau côtière","lng":"-2.07065981728","lat":"46.77984820847","idSite":"000953","siteDetails":{"surveillance":true,"amenities":true,"animalsAllowed":false,"showers":false,"drinkingWater":true,"wheelchairAccess":true,"toilets":true,"lifeguard":true,"seasonStart":"2025-06-15T00:00:00.000Z","seasonEnd":"2025-09-15T00:00:00.000Z","lastWaterQuality":"Excellent","lastTestDate":"2025-09-01T00:00:00.000Z"},"score":85,"images":[{"url":"https://upload.wikimedia.org/wikipedia/commons/b/b5/Plage_de_Saint_Jean_de_Monts.jpg","thumbUrl":"https://upload.wikimedia.org/wikipedia/commons/thumb/b/b5/Plage_de_Saint_Jean_de_Monts.jpg/960px-Plage_de_Saint_Jean_de_Monts.jpg","title":"Plage de Saint Jean de Monts.jpg","description":"vue de la plage de Saint Jean de Monts en juillet 2024","license":"CC0","score":35}],"department":"Vendée","slug":"la-grande-plage-saint-jean-de-monts"}