{"region":"Bourgogne-Franche-Comté","code":"FRC2125463D025250","situationUpdate":"Pas de changement","name":"La Plage de Pont de Roide","insee":"25463","city":"Pont-de-Roide-Vermondans","ueDeclarationDate":"01/01/1995","type":"Rivière","lng":"6.76651722673","lat":"47.37684789023","idSite":"001378","siteDetails":{"surveillance":true,"amenities":true,"animalsAllowed":true,"showers":false,"drinkingWater":true,"wheelchairAccess":false,"toilets":true,"lifeguard":true,"seasonStart":"2025-06-03T00:00:00.000Z","seasonEnd":"2025-08-31T00:00:00.000Z","lastWaterQuality":null,"lastTestDate":null},"score":60,"images":[{"url":"https://www.montagnes-du-jura.fr/uploads/external/b32a9977963954c496af59d062d60b51-313020720-11-1440x900.jpg","title":"","description":"","license":"manual","score":999}],"department":"Doubs","slug":"la-plage-de-pont-de-roide-pont-de-roide-vermondans"}