{"region":"Occitanie","code":"FRJ2432412D032125","situationUpdate":"Pas de changement","name":"Lac de Saramon","insee":"32412","city":"Saramon","ueDeclarationDate":"01/01/1992","type":"Lac","lng":"0.76396087031","lat":"43.51413273546","idSite":"000370","siteDetails":{"surveillance":true,"amenities":true,"animalsAllowed":true,"showers":true,"drinkingWater":true,"wheelchairAccess":true,"toilets":true,"lifeguard":true,"seasonStart":"2026-06-20T00:00:00.000Z","seasonEnd":"2026-08-30T00:00:00.000Z","lastWaterQuality":"Excellent","lastTestDate":"2025-09-01T00:00:00.000Z"},"score":90,"images":[],"department":"Gers","slug":"lac-de-saramon-saramon"}