{"region":"Occitanie","code":"FRJ2212270D012111","situationUpdate":"Pas de changement","name":"Lac Cisba","insee":"12270","city":"Severac d'Aveyron","ueDeclarationDate":"01/01/1999","type":"Lac","lng":"3.04496746651","lat":"44.32667908866","idSite":"001703","siteDetails":{"surveillance":true,"amenities":true,"animalsAllowed":true,"showers":false,"drinkingWater":false,"wheelchairAccess":false,"toilets":false,"lifeguard":false,"seasonStart":"2025-06-29T00:00:00.000Z","seasonEnd":"2025-08-31T00:00:00.000Z","lastWaterQuality":"Excellent","lastTestDate":"2025-09-01T00:00:00.000Z"},"score":75,"images":[{"url":"https://upload.wikimedia.org/wikipedia/commons/f/f7/Terril_lac_Cisba%2C_12.jpg","thumbUrl":"https://upload.wikimedia.org/wikipedia/commons/thumb/f/f7/Terril_lac_Cisba%2C_12.jpg/960px-Terril_lac_Cisba%2C_12.jpg","title":"Terril lac Cisba, 12.jpg","description":"Vestiges du terril dit de la « Grande Paroisse », lac de la Cisba, Aveyron, tel qu’il apparaissait à l’été 2013.\nLe lac artificiel présente une profondeur maximale de 5,80 m.","license":"CC BY-SA 4.0","score":35},{"url":"https://upload.wikimedia.org/wikipedia/commons/9/9b/Terrain_volley%2C_lac_Cisba_-_12.jpg","thumbUrl":"https://upload.wikimedia.org/wikipedia/commons/thumb/9/9b/Terrain_volley%2C_lac_Cisba_-_12.jpg/960px-Terrain_volley%2C_lac_Cisba_-_12.jpg","title":"Terrain volley, lac Cisba - 12.jpg","description":"Qui aurait cru qu’on puisse jouer au volley dans une ancienne carrière de schiste ?","license":"CC BY-SA 4.0","score":20}],"department":"Aveyron","slug":"lac-cisba-severac-d-aveyron"}