{"region":"Occitanie","code":"FRJ1230231D030299","situationUpdate":"Pas de changement","name":"Le Rocher des Fees","insee":"30231","city":"Saint-Andre-de-Valborgne","ueDeclarationDate":"01/01/1997","type":"Rivière","lng":"3.66349869320","lat":"44.16396711871","idSite":"002036","siteDetails":{"surveillance":false,"amenities":false,"animalsAllowed":true,"showers":false,"drinkingWater":false,"wheelchairAccess":false,"toilets":false,"lifeguard":false,"seasonStart":"2025-07-01T00:00:00.000Z","seasonEnd":"2025-08-31T00:00:00.000Z","lastWaterQuality":"Suffisant","lastTestDate":"2025-09-01T00:00:00.000Z"},"score":-20,"department":"Gard","slug":"le-rocher-des-fees-saint-andre-de-valborgne"}