{"region":"Bretagne","code":"FRH0335358M035635","situationUpdate":"Pas de changement","name":"Le Vigneux","insee":"35358","city":"Ville-Es-Nonais (La)","ueDeclarationDate":"01/01/1991","type":"Eau de transition","lng":"-1.96450284873","lat":"48.54441203952","idSite":"000868","siteDetails":{"surveillance":false,"amenities":true,"animalsAllowed":false,"showers":true,"drinkingWater":true,"wheelchairAccess":true,"toilets":true,"lifeguard":false,"seasonStart":"2025-06-15T00:00:00.000Z","seasonEnd":"2025-09-15T00:00:00.000Z","lastWaterQuality":"Bon","lastTestDate":"2025-09-01T00:00:00.000Z"},"score":50,"images":[{"url":"https://upload.wikimedia.org/wikipedia/commons/b/b2/20190428_07_Le_Port_Saint-Jean_-_La_Rance_%2846968402914%29.jpg","thumbUrl":"https://upload.wikimedia.org/wikipedia/commons/thumb/b/b2/20190428_07_Le_Port_Saint-Jean_-_La_Rance_%2846968402914%29.jpg/960px-20190428_07_Le_Port_Saint-Jean_-_La_Rance_%2846968402914%29.jpg","title":"20190428 07 Le Port Saint-Jean - La Rance (46968402914).jpg","description":"Sometimes even a rainy day has beauty","license":"CC BY 2.0","score":20}],"department":"Ille-et-Vilaine","slug":"le-vigneux-ville-es-nonais-la"}