{"region":"Pays de la Loire","code":"FRG0144049M044170","situationUpdate":"Pas de changement","name":"Les Sables Menus","insee":"44049","city":"Croisic (Le)","ueDeclarationDate":"01/01/1991","type":"Eau côtière","lng":"-2.52355362018","lat":"47.28688911974","idSite":"000522","siteDetails":{"surveillance":false,"amenities":true,"animalsAllowed":false,"showers":false,"drinkingWater":false,"wheelchairAccess":false,"toilets":true,"lifeguard":false,"seasonStart":"2025-06-15T00:00:00.000Z","seasonEnd":"2025-09-15T00:00:00.000Z","lastWaterQuality":"Bon","lastTestDate":"2025-09-01T00:00:00.000Z"},"score":65,"images":[{"url":"https://upload.wikimedia.org/wikipedia/commons/a/a7/Littoral_Sud_Presqu%27%C3%8Ele_-_Le_Croisic_%28FR44%29_-_2022-09-17_-_18.jpg","thumbUrl":"https://upload.wikimedia.org/wikipedia/commons/thumb/a/a7/Littoral_Sud_Presqu%27%C3%8Ele_-_Le_Croisic_%28FR44%29_-_2022-09-17_-_18.jpg/960px-Littoral_Sud_Presqu%27%C3%8Ele_-_Le_Croisic_%28FR44%29_-_2022-09-17_-_18.jpg","title":"Littoral Sud Presqu'Île - Le Croisic (FR44) - 2022-09-17 - 18.jpg","description":"Littoral au sud de la presqu'Île, Le Croisic.","license":"CC BY-SA 4.0","score":60},{"url":"https://upload.wikimedia.org/wikipedia/commons/b/b9/Littoral_Sud_Presqu%27%C3%8Ele_-_Le_Croisic_%28FR44%29_-_2022-09-17_-_19.jpg","thumbUrl":"https://upload.wikimedia.org/wikipedia/commons/thumb/b/b9/Littoral_Sud_Presqu%27%C3%8Ele_-_Le_Croisic_%28FR44%29_-_2022-09-17_-_19.jpg/960px-Littoral_Sud_Presqu%27%C3%8Ele_-_Le_Croisic_%28FR44%29_-_2022-09-17_-_19.jpg","title":"Littoral Sud Presqu'Île - Le Croisic (FR44) - 2022-09-17 - 19.jpg","description":"Littoral au sud de la presqu'Île, Le Croisic.","license":"CC BY-SA 4.0","score":60},{"url":"https://upload.wikimedia.org/wikipedia/commons/f/ff/Littoral_Sud_Presqu%27%C3%8Ele_-_Le_Croisic_%28FR44%29_-_2022-09-17_-_20.jpg","thumbUrl":"https://upload.wikimedia.org/wikipedia/commons/thumb/f/ff/Littoral_Sud_Presqu%27%C3%8Ele_-_Le_Croisic_%28FR44%29_-_2022-09-17_-_20.jpg/960px-Littoral_Sud_Presqu%27%C3%8Ele_-_Le_Croisic_%28FR44%29_-_2022-09-17_-_20.jpg","title":"Littoral Sud Presqu'Île - Le Croisic (FR44) - 2022-09-17 - 20.jpg","description":"Littoral au sud de la presqu'Île, Le Croisic.","license":"CC BY-SA 4.0","score":60},{"url":"https://upload.wikimedia.org/wikipedia/commons/2/27/Littoral_Sud_Presqu%27%C3%8Ele_-_Le_Croisic_%28FR44%29_-_2022-09-17_-_21.jpg","thumbUrl":"https://upload.wikimedia.org/wikipedia/commons/thumb/2/27/Littoral_Sud_Presqu%27%C3%8Ele_-_Le_Croisic_%28FR44%29_-_2022-09-17_-_21.jpg/960px-Littoral_Sud_Presqu%27%C3%8Ele_-_Le_Croisic_%28FR44%29_-_2022-09-17_-_21.jpg","title":"Littoral Sud Presqu'Île - Le Croisic (FR44) - 2022-09-17 - 21.jpg","description":"Littoral au sud de la presqu'Île, Le Croisic.","license":"CC BY-SA 4.0","score":60},{"url":"https://upload.wikimedia.org/wikipedia/commons/8/8a/Littoral_Sud_Presqu%27%C3%8Ele_-_Le_Croisic_%28FR44%29_-_2022-09-17_-_22.jpg","thumbUrl":"https://upload.wikimedia.org/wikipedia/commons/thumb/8/8a/Littoral_Sud_Presqu%27%C3%8Ele_-_Le_Croisic_%28FR44%29_-_2022-09-17_-_22.jpg/960px-Littoral_Sud_Presqu%27%C3%8Ele_-_Le_Croisic_%28FR44%29_-_2022-09-17_-_22.jpg","title":"Littoral Sud Presqu'Île - Le Croisic (FR44) - 2022-09-17 - 22.jpg","description":"Littoral au sud de la presqu'Île, Le Croisic.","license":"CC BY-SA 4.0","score":60},{"url":"https://upload.wikimedia.org/wikipedia/commons/d/dd/Littoral_Sud_Presqu%27%C3%8Ele_-_Le_Croisic_%28FR44%29_-_2022-09-17_-_25.jpg","thumbUrl":"https://upload.wikimedia.org/wikipedia/commons/thumb/d/dd/Littoral_Sud_Presqu%27%C3%8Ele_-_Le_Croisic_%28FR44%29_-_2022-09-17_-_25.jpg/960px-Littoral_Sud_Presqu%27%C3%8Ele_-_Le_Croisic_%28FR44%29_-_2022-09-17_-_25.jpg","title":"Littoral Sud Presqu'Île - Le Croisic (FR44) - 2022-09-17 - 25.jpg","description":"Littoral au sud de la presqu'Île, Le Croisic.","license":"CC BY-SA 4.0","score":60},{"url":"https://upload.wikimedia.org/wikipedia/commons/9/9b/Littoral_Sud_Presqu%27%C3%8Ele_-_Le_Croisic_%28FR44%29_-_2022-09-17_-_23.jpg","thumbUrl":"https://upload.wikimedia.org/wikipedia/commons/thumb/9/9b/Littoral_Sud_Presqu%27%C3%8Ele_-_Le_Croisic_%28FR44%29_-_2022-09-17_-_23.jpg/960px-Littoral_Sud_Presqu%27%C3%8Ele_-_Le_Croisic_%28FR44%29_-_2022-09-17_-_23.jpg","title":"Littoral Sud Presqu'Île - Le Croisic (FR44) - 2022-09-17 - 23.jpg","description":"Littoral au sud de la presqu'Île, Le Croisic.","license":"CC BY-SA 4.0","score":60},{"url":"https://upload.wikimedia.org/wikipedia/commons/c/ce/Littoral_Sud_Presqu%27%C3%8Ele_-_Le_Croisic_%28FR44%29_-_2022-09-17_-_24.jpg","thumbUrl":"https://upload.wikimedia.org/wikipedia/commons/thumb/c/ce/Littoral_Sud_Presqu%27%C3%8Ele_-_Le_Croisic_%28FR44%29_-_2022-09-17_-_24.jpg/960px-Littoral_Sud_Presqu%27%C3%8Ele_-_Le_Croisic_%28FR44%29_-_2022-09-17_-_24.jpg","title":"Littoral Sud Presqu'Île - Le Croisic (FR44) - 2022-09-17 - 24.jpg","description":"Littoral au sud de la presqu'Île, Le Croisic.","license":"CC BY-SA 4.0","score":60},{"url":"https://upload.wikimedia.org/wikipedia/commons/e/ed/Littoral_Sud_Presqu%27%C3%8Ele_-_Le_Croisic_%28FR44%29_-_2022-09-17_-_26.jpg","thumbUrl":"https://upload.wikimedia.org/wikipedia/commons/thumb/e/ed/Littoral_Sud_Presqu%27%C3%8Ele_-_Le_Croisic_%28FR44%29_-_2022-09-17_-_26.jpg/960px-Littoral_Sud_Presqu%27%C3%8Ele_-_Le_Croisic_%28FR44%29_-_2022-09-17_-_26.jpg","title":"Littoral Sud Presqu'Île - Le Croisic (FR44) - 2022-09-17 - 26.jpg","description":"Littoral au sud de la presqu'Île, Le Croisic.","license":"CC BY-SA 4.0","score":60},{"url":"https://upload.wikimedia.org/wikipedia/commons/2/27/Mobeye-%C3%89t%C3%A9DesVilles-Le_Croisic-394.jpg","thumbUrl":"https://upload.wikimedia.org/wikipedia/commons/thumb/2/27/Mobeye-%C3%89t%C3%A9DesVilles-Le_Croisic-394.jpg/960px-Mobeye-%C3%89t%C3%A9DesVilles-Le_Croisic-394.jpg","title":"Mobeye-ÉtéDesVilles-Le Croisic-394.jpg","description":"La plage","license":"CC BY 4.0","score":35},{"url":"https://upload.wikimedia.org/wikipedia/commons/2/2b/Baie_de_la_Nicouse%2C_Le_Croisic%2C_Pays_de_la_Loire%2C_France_-_panoramio.jpg","thumbUrl":"https://upload.wikimedia.org/wikipedia/commons/thumb/2/2b/Baie_de_la_Nicouse%2C_Le_Croisic%2C_Pays_de_la_Loire%2C_France_-_panoramio.jpg/960px-Baie_de_la_Nicouse%2C_Le_Croisic%2C_Pays_de_la_Loire%2C_France_-_panoramio.jpg","title":"Baie de la Nicouse, Le Croisic, Pays de la Loire, France - panoramio.jpg","description":"Baie de la Nicouse, Le Croisic, Pays de la Loire, France","license":"CC BY-SA 3.0","score":20},{"url":"https://upload.wikimedia.org/wikipedia/commons/f/f6/Le_Croisic%2C_Baie_de_la_Nicouse_-_panoramio.jpg","thumbUrl":"https://upload.wikimedia.org/wikipedia/commons/thumb/f/f6/Le_Croisic%2C_Baie_de_la_Nicouse_-_panoramio.jpg/960px-Le_Croisic%2C_Baie_de_la_Nicouse_-_panoramio.jpg","title":"Le Croisic, Baie de la Nicouse - panoramio.jpg","description":"Le Croisic, Baie de la Nicouse","license":"CC BY-SA 3.0","score":20},{"url":"https://upload.wikimedia.org/wikipedia/commons/c/c7/Baie_de_la_Nicouse%2C_Le_Croisic%2C_Pays_de_la_Loire%2C_France_-_panoramio_-_M.Str%C4%AB%C4%B7is.jpg","thumbUrl":"https://upload.wikimedia.org/wikipedia/commons/thumb/c/c7/Baie_de_la_Nicouse%2C_Le_Croisic%2C_Pays_de_la_Loire%2C_France_-_panoramio_-_M.Str%C4%AB%C4%B7is.jpg/960px-Baie_de_la_Nicouse%2C_Le_Croisic%2C_Pays_de_la_Loire%2C_France_-_panoramio_-_M.Str%C4%AB%C4%B7is.jpg","title":"Baie de la Nicouse, Le Croisic, Pays de la Loire, France - panoramio - M.Strīķis.jpg","description":"Baie de la Nicouse, Le Croisic, Pays de la Loire, France","license":"CC BY-SA 3.0","score":20},{"url":"https://upload.wikimedia.org/wikipedia/commons/e/eb/Baie_de_la_Nicouse%2C_Le_Croisic%2C_Pays_de_la_Loire%2C_France_-_panoramio_-_M.Str%C4%AB%C4%B7is_%281%29.jpg","thumbUrl":"https://upload.wikimedia.org/wikipedia/commons/thumb/e/eb/Baie_de_la_Nicouse%2C_Le_Croisic%2C_Pays_de_la_Loire%2C_France_-_panoramio_-_M.Str%C4%AB%C4%B7is_%281%29.jpg/960px-Baie_de_la_Nicouse%2C_Le_Croisic%2C_Pays_de_la_Loire%2C_France_-_panoramio_-_M.Str%C4%AB%C4%B7is_%281%29.jpg","title":"Baie de la Nicouse, Le Croisic, Pays de la Loire, France - panoramio - M.Strīķis (1).jpg","description":"Baie de la Nicouse, Le Croisic, Pays de la Loire, France","license":"CC BY-SA 3.0","score":20},{"url":"https://upload.wikimedia.org/wikipedia/commons/e/ed/Baie_de_la_Nicouse%2C_Le_Croisic%2C_Pays_de_la_Loire%2C_France_-_panoramio_-_M.Str%C4%AB%C4%B7is_%282%29.jpg","thumbUrl":"https://upload.wikimedia.org/wikipedia/commons/thumb/e/ed/Baie_de_la_Nicouse%2C_Le_Croisic%2C_Pays_de_la_Loire%2C_France_-_panoramio_-_M.Str%C4%AB%C4%B7is_%282%29.jpg/960px-Baie_de_la_Nicouse%2C_Le_Croisic%2C_Pays_de_la_Loire%2C_France_-_panoramio_-_M.Str%C4%AB%C4%B7is_%282%29.jpg","title":"Baie de la Nicouse, Le Croisic, Pays de la Loire, France - panoramio - M.Strīķis (2).jpg","description":"Baie de la Nicouse, Le Croisic, Pays de la Loire, France","license":"CC BY-SA 3.0","score":20},{"url":"https://upload.wikimedia.org/wikipedia/commons/7/7b/Baie_de_la_Nicouse%2C_Le_Croisic%2C_Pays_de_la_Loire%2C_France_-_panoramio_-_M.Str%C4%AB%C4%B7is_%283%29.jpg","thumbUrl":"https://upload.wikimedia.org/wikipedia/commons/thumb/7/7b/Baie_de_la_Nicouse%2C_Le_Croisic%2C_Pays_de_la_Loire%2C_France_-_panoramio_-_M.Str%C4%AB%C4%B7is_%283%29.jpg/960px-Baie_de_la_Nicouse%2C_Le_Croisic%2C_Pays_de_la_Loire%2C_France_-_panoramio_-_M.Str%C4%AB%C4%B7is_%283%29.jpg","title":"Baie de la Nicouse, Le Croisic, Pays de la Loire, France - panoramio - M.Strīķis (3).jpg","description":"Baie de la Nicouse, Le Croisic, Pays de la Loire, France","license":"CC BY-SA 3.0","score":20},{"url":"https://upload.wikimedia.org/wikipedia/commons/f/ff/Baie_de_la_Nicouse%2C_Le_Croisic%2C_Pays_de_la_Loire%2C_France_-_panoramio_-_M.Str%C4%AB%C4%B7is_%284%29.jpg","thumbUrl":"https://upload.wikimedia.org/wikipedia/commons/thumb/f/ff/Baie_de_la_Nicouse%2C_Le_Croisic%2C_Pays_de_la_Loire%2C_France_-_panoramio_-_M.Str%C4%AB%C4%B7is_%284%29.jpg/960px-Baie_de_la_Nicouse%2C_Le_Croisic%2C_Pays_de_la_Loire%2C_France_-_panoramio_-_M.Str%C4%AB%C4%B7is_%284%29.jpg","title":"Baie de la Nicouse, Le Croisic, Pays de la Loire, France - panoramio - M.Strīķis (4).jpg","description":"Baie de la Nicouse, Le Croisic, Pays de la Loire, France","license":"CC BY-SA 3.0","score":20},{"url":"https://upload.wikimedia.org/wikipedia/commons/6/64/Baie_de_la_Nicouse%2C_Le_Croisic%2C_Pays_de_la_Loire%2C_France_-_panoramio_-_M.Str%C4%AB%C4%B7is_%285%29.jpg","thumbUrl":"https://upload.wikimedia.org/wikipedia/commons/thumb/6/64/Baie_de_la_Nicouse%2C_Le_Croisic%2C_Pays_de_la_Loire%2C_France_-_panoramio_-_M.Str%C4%AB%C4%B7is_%285%29.jpg/960px-Baie_de_la_Nicouse%2C_Le_Croisic%2C_Pays_de_la_Loire%2C_France_-_panoramio_-_M.Str%C4%AB%C4%B7is_%285%29.jpg","title":"Baie de la Nicouse, Le Croisic, Pays de la Loire, France - panoramio - M.Strīķis (5).jpg","description":"Baie de la Nicouse, Le Croisic, Pays de la Loire, France","license":"CC BY-SA 3.0","score":20},{"url":"https://upload.wikimedia.org/wikipedia/commons/e/e2/Chaise_Le_Croisic.jpg","thumbUrl":"https://upload.wikimedia.org/wikipedia/commons/thumb/e/e2/Chaise_Le_Croisic.jpg/960px-Chaise_Le_Croisic.jpg","title":"Chaise Le Croisic.jpg","description":"Une chaise qui permet d'avoir une vue panoramique.","license":"CC BY-SA 4.0","score":5}],"department":"Loire-Atlantique","slug":"les-sables-menus-croisic-le","nearbySpots":[{"slug":"port-lin-croisic-le","name":"Port Lin","city":"Croisic (Le)","department":"Loire-Atlantique","type":"Eau côtière","distanceKm":0.9,"score":85,"lastWaterQuality":"Bon","thumbUrl":"https://upload.wikimedia.org/wikipedia/commons/thumb/4/4a/Littoral_Sud_Presqu%27%C3%8Ele_-_Le_Croisic_%28FR44%29_-_2022-09-17_-_28.jpg/960px-Littoral_Sud_Presqu%27%C3%8Ele_-_Le_Croisic_%28FR44%29_-_2022-09-17_-_28.jpg"},{"slug":"saint-jean-de-dieu-croisic-le","name":"Saint Jean de Dieu","city":"Croisic (Le)","department":"Loire-Atlantique","type":"Eau côtière","distanceKm":1.7,"score":75,"lastWaterQuality":"Bon","thumbUrl":"https://upload.wikimedia.org/wikipedia/commons/thumb/d/de/Plage_du_Croisic_%2814232434155%29.jpg/960px-Plage_du_Croisic_%2814232434155%29.jpg"},{"slug":"le-castouillet-baie-croisic-le","name":"Le Castouillet (Baie)","city":"Croisic (Le)","department":"Loire-Atlantique","type":"Eau côtière","distanceKm":1.8,"score":-5,"lastWaterQuality":"Suffisant"},{"slug":"port-aux-rocs-croisic-le","name":"Port aux Rocs","city":"Croisic (Le)","department":"Loire-Atlantique","type":"Eau côtière","distanceKm":2.1,"score":25,"lastWaterQuality":"Excellent","thumbUrl":"https://upload.wikimedia.org/wikipedia/commons/thumb/8/8c/Littoral_Port_Val_-_Le_Croisic_%28FR44%29_-_2022-09-17_-_2.jpg/960px-Littoral_Port_Val_-_Le_Croisic_%28FR44%29_-_2022-09-17_-_2.jpg"},{"slug":"valentin-batz-sur-mer","name":"Valentin","city":"Batz-sur-Mer","department":"Loire-Atlantique","type":"Eau côtière","distanceKm":2.2,"score":90,"lastWaterQuality":"Excellent","thumbUrl":"https://upload.wikimedia.org/wikipedia/commons/thumb/a/a1/Sunset_in_Batz-sur-Mer.jpg/960px-Sunset_in_Batz-sur-Mer.jpg"},{"slug":"saint-michel-batz-sur-mer","name":"Saint Michel","city":"Batz-sur-Mer","department":"Loire-Atlantique","type":"Eau côtière","distanceKm":3.5,"score":40,"lastWaterQuality":"Excellent","thumbUrl":"https://upload.wikimedia.org/wikipedia/commons/thumb/f/f3/Saint-Michel_beach%2C_Batz-sur-Mer.jpg/960px-Saint-Michel_beach%2C_Batz-sur-Mer.jpg"},{"slug":"pen-bron-turballe-la","name":"Pen Bron","city":"Turballe (La)","department":"Loire-Atlantique","type":"Eau côtière","distanceKm":4.8,"score":65,"lastWaterQuality":"Excellent"},{"slug":"la-govelle-batz-sur-mer","name":"La Govelle","city":"Batz-sur-Mer","department":"Loire-Atlantique","type":"Eau côtière","distanceKm":5.6,"score":90,"lastWaterQuality":"Excellent","thumbUrl":"https://upload.wikimedia.org/wikipedia/commons/thumb/e/ea/Baie_du_Maneric%2C_Batz-sur-Mer%2C_different_crop.jpg/960px-Baie_du_Maneric%2C_Batz-sur-Mer%2C_different_crop.jpg"}]}