{"region":"Occitanie","code":"FRJ2212070D012062","situationUpdate":"Pas de changement","name":"Pailhas","insee":"12070","city":"Compeyre","ueDeclarationDate":"01/01/1991","type":"Rivière","lng":"3.12485374208","lat":"44.17098809266","idSite":"001699","siteDetails":{"surveillance":false,"amenities":false,"animalsAllowed":true,"showers":false,"drinkingWater":false,"wheelchairAccess":false,"toilets":false,"lifeguard":false,"seasonStart":"2025-06-29T00:00:00.000Z","seasonEnd":"2025-08-31T00:00:00.000Z","lastWaterQuality":"Excellent","lastTestDate":"2025-09-01T00:00:00.000Z"},"score":20,"images":[{"url":"https://upload.wikimedia.org/wikipedia/commons/c/c8/Renovated_old_iron_bridge_over_the_Tarn_river_at_La_Cresse_-_panoramio.jpg","thumbUrl":"https://upload.wikimedia.org/wikipedia/commons/thumb/c/c8/Renovated_old_iron_bridge_over_the_Tarn_river_at_La_Cresse_-_panoramio.jpg/960px-Renovated_old_iron_bridge_over_the_Tarn_river_at_La_Cresse_-_panoramio.jpg","title":"Renovated old iron bridge over the Tarn river at La Cresse - panoramio.jpg","description":"Renovated old iron bridge over the Tarn river at La Cresse","license":"CC BY 3.0","score":10},{"url":"https://upload.wikimedia.org/wikipedia/commons/d/dd/View_on_La_Cresse_03.jpg","thumbUrl":"https://upload.wikimedia.org/wikipedia/commons/thumb/d/dd/View_on_La_Cresse_03.jpg/960px-View_on_La_Cresse_03.jpg","title":"View on La Cresse 03.jpg","description":"View on La Cresse, Aveyron, France","license":"CC BY-SA 4.0","score":5},{"url":"https://upload.wikimedia.org/wikipedia/commons/6/66/View_on_La_Cresse_02.jpg","thumbUrl":"https://upload.wikimedia.org/wikipedia/commons/thumb/6/66/View_on_La_Cresse_02.jpg/960px-View_on_La_Cresse_02.jpg","title":"View on La Cresse 02.jpg","description":"View on La Cresse, Aveyron, France","license":"CC BY-SA 4.0","score":5},{"url":"https://upload.wikimedia.org/wikipedia/commons/5/5b/View_on_La_Cresse_01.jpg","thumbUrl":"https://upload.wikimedia.org/wikipedia/commons/thumb/5/5b/View_on_La_Cresse_01.jpg/960px-View_on_La_Cresse_01.jpg","title":"View on La Cresse 01.jpg","description":"View on La Cresse, Aveyron, France","license":"CC BY-SA 4.0","score":5},{"url":"https://upload.wikimedia.org/wikipedia/commons/d/d3/View_on_La_Cresse_04.jpg","thumbUrl":"https://upload.wikimedia.org/wikipedia/commons/thumb/d/d3/View_on_La_Cresse_04.jpg/960px-View_on_La_Cresse_04.jpg","title":"View on La Cresse 04.jpg","description":"View on La Cresse, Aveyron, France","license":"CC BY-SA 4.0","score":5}],"department":"Aveyron","slug":"pailhas-compeyre"}