{"region":"Occitanie","code":"FRJ1448095D048124","situationUpdate":"Pas de changement","name":"Parc Wunsiedel","insee":"48095","city":"Mende","ueDeclarationDate":"05/07/2021","type":"Rivière","lng":"3.47902327176","lat":"44.51693793356","idSite":"006437","siteDetails":{"surveillance":true,"amenities":true,"animalsAllowed":true,"showers":false,"drinkingWater":false,"wheelchairAccess":false,"toilets":false,"lifeguard":false,"seasonStart":"2025-07-01T00:00:00.000Z","seasonEnd":"2025-08-31T00:00:00.000Z","lastWaterQuality":null,"lastTestDate":null},"score":35,"images":[],"department":"Lozère","slug":"parc-wunsiedel-mende"}