{"region":"Bretagne","code":"FRH0229037M029808","situationUpdate":"Pas de changement","name":"Pen Morvan","insee":"29037","city":"Combrit","ueDeclarationDate":"15/06/2011","type":"Eau côtière","lng":"-4.12322979279","lat":"47.86447059824","idSite":"002406","siteDetails":{"surveillance":true,"amenities":false,"animalsAllowed":true,"showers":false,"drinkingWater":false,"wheelchairAccess":false,"toilets":false,"lifeguard":true,"seasonStart":"2025-06-15T00:00:00.000Z","seasonEnd":"2025-09-15T00:00:00.000Z","lastWaterQuality":"Excellent","lastTestDate":"2025-09-01T00:00:00.000Z"},"score":60,"images":[{"url":"https://upload.wikimedia.org/wikipedia/commons/1/1f/Heol_Beg_Kombrid.jpg","thumbUrl":"https://upload.wikimedia.org/wikipedia/commons/thumb/1/1f/Heol_Beg_Kombrid.jpg/960px-Heol_Beg_Kombrid.jpg","title":"Heol Beg Kombrid.jpg","description":"Sunny ocean in Combrit's point (Finistère, Brittany, France)","license":"CC BY-SA 3.0","score":35}],"department":"Finistère","slug":"pen-morvan-combrit"}