{"region":"Nouvelle-Aquitaine","code":"FRI3217300M017015","situationUpdate":"Pas de changement","name":"Plage de Chef de Baie","insee":"17300","city":"Rochelle (La)","ueDeclarationDate":"01/01/1991","type":"Eau côtière","lng":"-1.21051367881","lat":"46.14744132006","idSite":"000584","siteDetails":{"surveillance":true,"amenities":true,"animalsAllowed":true,"showers":true,"drinkingWater":true,"wheelchairAccess":true,"toilets":true,"lifeguard":true,"seasonStart":"2026-06-15T00:00:00.000Z","seasonEnd":"2026-09-13T00:00:00.000Z","lastWaterQuality":"Excellent","lastTestDate":"2025-09-01T00:00:00.000Z"},"score":90,"images":[{"url":"https://upload.wikimedia.org/wikipedia/commons/5/54/Entrep%C3%B4ts.jpg","thumbUrl":"https://upload.wikimedia.org/wikipedia/commons/thumb/5/54/Entrep%C3%B4ts.jpg/960px-Entrep%C3%B4ts.jpg","title":"Entrepôts.jpg","description":"La différence entre les palettes reçues, et les palettes triées prêtes à l'envoi.","license":"CC BY-SA 4.0","score":5}],"department":"Charente-Maritime","slug":"plage-de-chef-de-baie-rochelle-la"}