{"region":"Occitanie","code":"FRJ2546313D046038","situationUpdate":"Pas de changement","name":"Plan d'Eau Mas de la Croux","insee":"46313","city":"Tauriac","ueDeclarationDate":"01/01/1991","type":"Lac","lng":"1.77363636589","lat":"44.90480761762","idSite":"000668","siteDetails":{"surveillance":true,"amenities":true,"animalsAllowed":true,"showers":true,"drinkingWater":true,"wheelchairAccess":false,"toilets":true,"lifeguard":true,"seasonStart":"2025-07-01T00:00:00.000Z","seasonEnd":"2025-08-31T00:00:00.000Z","lastWaterQuality":"Excellent","lastTestDate":"2025-09-01T00:00:00.000Z"},"score":85,"images":[],"department":"Lot","slug":"plan-d-eau-mas-de-la-croux-tauriac","nearbySpots":[{"slug":"les-granges-vayrac","name":"Les Granges","city":"Vayrac","department":"Lot","type":"Rivière","distanceKm":7.1,"score":10,"lastWaterQuality":"Excellent"},{"slug":"la-plage-altillac","name":"La Plage","city":"Altillac","department":"Corrèze","type":"Rivière","distanceKm":9.9,"score":25,"lastWaterQuality":"Bon","thumbUrl":"https://upload.wikimedia.org/wikipedia/commons/thumb/b/b7/Gabare_op_de_Dordogne%2C_Frankrijk_2010.jpg/960px-Gabare_op_de_Dordogne%2C_Frankrijk_2010.jpg"},{"slug":"gluges-montvalent","name":"Gluges","city":"Montvalent","department":"Lot","type":"Rivière","distanceKm":12,"score":70,"lastWaterQuality":"Excellent"},{"slug":"le-vieux-chene-montvalent","name":"Le Vieux Chene","city":"Montvalent","department":"Lot","type":"Rivière","distanceKm":13,"score":10,"lastWaterQuality":"Excellent"},{"slug":"le-port-creysse","name":"Le Port","city":"Creysse","department":"Lot","type":"Rivière","distanceKm":14.2,"score":10,"lastWaterQuality":"Excellent"},{"slug":"etang-du-moulin-camps-saint-mathurin-leobazel","name":"Etang du Moulin","city":"Camps-Saint-Mathurin-Leobazel","department":"Corrèze","type":"Lac","distanceKm":18.9,"score":80,"lastWaterQuality":"Excellent"},{"slug":"la-bourgnette-a-meyraguet-lacave","name":"La Bourgnette a Meyraguet","city":"Lacave","department":"Lot","type":"Rivière","distanceKm":20.4,"score":20,"lastWaterQuality":"Excellent","thumbUrl":"https://upload.wikimedia.org/wikipedia/commons/thumb/f/f4/Dordogne_River_01.jpg/960px-Dordogne_River_01.jpg"},{"slug":"le-tolerme-senaillac-latronquiere","name":"Le Tolerme","city":"Senaillac-Latronquiere","department":"Lot","type":"Lac","distanceKm":23.3,"score":85,"lastWaterQuality":"Excellent"}]}