{"region":"Auvergne-Rhône-Alpes","code":"FRK1463038D063040","situationUpdate":"Pas de changement","name":"Plan d'Eau de Super Besse","insee":"63038","city":"Besse-et-Saint-Anastaise","ueDeclarationDate":"01/01/1992","type":"Lac","lng":"2.85517964218","lat":"45.50935040628","idSite":"004036","siteDetails":{"surveillance":true,"amenities":true,"animalsAllowed":false,"showers":true,"drinkingWater":true,"wheelchairAccess":false,"toilets":true,"lifeguard":true,"seasonStart":"2025-07-01T00:00:00.000Z","seasonEnd":"2025-08-31T00:00:00.000Z","lastWaterQuality":"Excellent","lastTestDate":"2025-09-01T00:00:00.000Z"},"score":95,"images":[{"url":"https://upload.wikimedia.org/wikipedia/commons/0/04/Lac_des_Hermines_%C3%A0_Super-Besse.jpg","thumbUrl":"https://upload.wikimedia.org/wikipedia/commons/thumb/0/04/Lac_des_Hermines_%C3%A0_Super-Besse.jpg/960px-Lac_des_Hermines_%C3%A0_Super-Besse.jpg","title":"Lac des Hermines à Super-Besse.jpg","description":"Lac des Hermines in Super-Besse (Puy-de-Dôme, France).","license":"Public domain","score":20}],"department":"Puy-de-Dôme","slug":"plan-d-eau-de-super-besse-besse-et-saint-anastaise"}