{"region":"Bourgogne-Franche-Comté","code":"FRC1371150D071211","situationUpdate":"Pas de changement","name":"Plan d'Eau des Sablons","insee":"71150","city":"Creches-sur-Saone","ueDeclarationDate":"01/01/1995","type":"Lac","lng":"4.80441042808","lat":"46.23783247785","idSite":"001291","siteDetails":{"surveillance":true,"amenities":true,"animalsAllowed":false,"showers":true,"drinkingWater":true,"wheelchairAccess":false,"toilets":false,"lifeguard":true,"seasonStart":"2025-07-01T00:00:00.000Z","seasonEnd":"2025-08-31T00:00:00.000Z","lastWaterQuality":"Excellent","lastTestDate":"2025-09-01T00:00:00.000Z"},"score":85,"images":[{"url":"https://upload.wikimedia.org/wikipedia/commons/4/4b/Rivi%C3%A8re_Sa%C3%B4ne_-_Cr%C3%AAches-sur-Sa%C3%B4ne_%28FR71%29_-_2024-05-08_-_1.jpg","thumbUrl":"https://upload.wikimedia.org/wikipedia/commons/thumb/4/4b/Rivi%C3%A8re_Sa%C3%B4ne_-_Cr%C3%AAches-sur-Sa%C3%B4ne_%28FR71%29_-_2024-05-08_-_1.jpg/960px-Rivi%C3%A8re_Sa%C3%B4ne_-_Cr%C3%AAches-sur-Sa%C3%B4ne_%28FR71%29_-_2024-05-08_-_1.jpg","title":"Rivière Saône - Crêches-sur-Saône (FR71) - 2024-05-08 - 1.jpg","description":"La Saône, Crêches-sur-Saône.","license":"CC BY-SA 4.0","score":35},{"url":"https://upload.wikimedia.org/wikipedia/commons/3/35/Rivi%C3%A8re_Sa%C3%B4ne_-_Cr%C3%AAches-sur-Sa%C3%B4ne_%28FR71%29_-_2024-05-08_-_2.jpg","thumbUrl":"https://upload.wikimedia.org/wikipedia/commons/thumb/3/35/Rivi%C3%A8re_Sa%C3%B4ne_-_Cr%C3%AAches-sur-Sa%C3%B4ne_%28FR71%29_-_2024-05-08_-_2.jpg/960px-Rivi%C3%A8re_Sa%C3%B4ne_-_Cr%C3%AAches-sur-Sa%C3%B4ne_%28FR71%29_-_2024-05-08_-_2.jpg","title":"Rivière Saône - Crêches-sur-Saône (FR71) - 2024-05-08 - 2.jpg","description":"La Saône, Crêches-sur-Saône.","license":"CC BY-SA 4.0","score":35},{"url":"https://upload.wikimedia.org/wikipedia/commons/7/72/Rivi%C3%A8re_Sa%C3%B4ne_-_Cormoranche-sur-Sa%C3%B4ne_%28FR01%29_-_2024-05-08_-_1.jpg","thumbUrl":"https://upload.wikimedia.org/wikipedia/commons/thumb/7/72/Rivi%C3%A8re_Sa%C3%B4ne_-_Cormoranche-sur-Sa%C3%B4ne_%28FR01%29_-_2024-05-08_-_1.jpg/960px-Rivi%C3%A8re_Sa%C3%B4ne_-_Cormoranche-sur-Sa%C3%B4ne_%28FR01%29_-_2024-05-08_-_1.jpg","title":"Rivière Saône - Cormoranche-sur-Saône (FR01) - 2024-05-08 - 1.jpg","description":"La Saône, Cormoranche-sur-Saône.","license":"CC BY-SA 4.0","score":35},{"url":"https://upload.wikimedia.org/wikipedia/commons/b/bb/Rivi%C3%A8re_Sa%C3%B4ne_-_Cormoranche-sur-Sa%C3%B4ne_%28FR01%29_-_2024-05-08_-_2.jpg","thumbUrl":"https://upload.wikimedia.org/wikipedia/commons/thumb/b/bb/Rivi%C3%A8re_Sa%C3%B4ne_-_Cormoranche-sur-Sa%C3%B4ne_%28FR01%29_-_2024-05-08_-_2.jpg/960px-Rivi%C3%A8re_Sa%C3%B4ne_-_Cormoranche-sur-Sa%C3%B4ne_%28FR01%29_-_2024-05-08_-_2.jpg","title":"Rivière Saône - Cormoranche-sur-Saône (FR01) - 2024-05-08 - 2.jpg","description":"La Saône, Cormoranche-sur-Saône.","license":"CC BY-SA 4.0","score":35},{"url":"https://upload.wikimedia.org/wikipedia/commons/8/8a/Rivi%C3%A8re_Sa%C3%B4ne_-_Cormoranche-sur-Sa%C3%B4ne_%28FR01%29_-_2025-06-07_-_1.jpg","thumbUrl":"https://upload.wikimedia.org/wikipedia/commons/thumb/8/8a/Rivi%C3%A8re_Sa%C3%B4ne_-_Cormoranche-sur-Sa%C3%B4ne_%28FR01%29_-_2025-06-07_-_1.jpg/960px-Rivi%C3%A8re_Sa%C3%B4ne_-_Cormoranche-sur-Sa%C3%B4ne_%28FR01%29_-_2025-06-07_-_1.jpg","title":"Rivière Saône - Cormoranche-sur-Saône (FR01) - 2025-06-07 - 1.jpg","description":"La Saône, Cormoranche-sur-Saône.","license":"CC BY-SA 4.0","score":35},{"url":"https://upload.wikimedia.org/wikipedia/commons/2/29/Rivi%C3%A8re_Sa%C3%B4ne_-_Cormoranche-sur-Sa%C3%B4ne_%28FR01%29_-_2025-06-07_-_2.jpg","thumbUrl":"https://upload.wikimedia.org/wikipedia/commons/thumb/2/29/Rivi%C3%A8re_Sa%C3%B4ne_-_Cormoranche-sur-Sa%C3%B4ne_%28FR01%29_-_2025-06-07_-_2.jpg/960px-Rivi%C3%A8re_Sa%C3%B4ne_-_Cormoranche-sur-Sa%C3%B4ne_%28FR01%29_-_2025-06-07_-_2.jpg","title":"Rivière Saône - Cormoranche-sur-Saône (FR01) - 2025-06-07 - 2.jpg","description":"La Saône, Cormoranche-sur-Saône.","license":"CC BY-SA 4.0","score":35},{"url":"https://upload.wikimedia.org/wikipedia/commons/b/ba/Confluence_Rivi%C3%A8res_Avanon_%26_Sa%C3%B4ne_-_Garnerans_%28FR01%29_-_2025-06-07_-_1.jpg","thumbUrl":"https://upload.wikimedia.org/wikipedia/commons/thumb/b/ba/Confluence_Rivi%C3%A8res_Avanon_%26_Sa%C3%B4ne_-_Garnerans_%28FR01%29_-_2025-06-07_-_1.jpg/960px-Confluence_Rivi%C3%A8res_Avanon_%26_Sa%C3%B4ne_-_Garnerans_%28FR01%29_-_2025-06-07_-_1.jpg","title":"Confluence Rivières Avanon & Saône - Garnerans (FR01) - 2025-06-07 - 1.jpg","description":"Confluence de l'Avanon et de la Saône, Garnerans.","license":"CC BY-SA 4.0","score":20},{"url":"https://upload.wikimedia.org/wikipedia/commons/4/42/Rivi%C3%A8re_Avanon_-_Garnerans_%28FR01%29_-_2025-06-07_-_1.jpg","thumbUrl":"https://upload.wikimedia.org/wikipedia/commons/thumb/4/42/Rivi%C3%A8re_Avanon_-_Garnerans_%28FR01%29_-_2025-06-07_-_1.jpg/960px-Rivi%C3%A8re_Avanon_-_Garnerans_%28FR01%29_-_2025-06-07_-_1.jpg","title":"Rivière Avanon - Garnerans (FR01) - 2025-06-07 - 1.jpg","description":"L'Avanon, Garnerans.","license":"CC BY-SA 4.0","score":20}],"department":"Saône-et-Loire","slug":"plan-d-eau-des-sablons-creches-sur-saone","nearbySpots":[{"slug":"graviere-varennes-les-macon","name":"Graviere","city":"Varennes-les-Macon","department":"Saône-et-Loire","type":"Lac","distanceKm":3.9,"score":30,"lastWaterQuality":"Excellent","thumbUrl":"https://upload.wikimedia.org/wikipedia/commons/thumb/b/b5/Place_19_Mars_1962_-_Varennes-l%C3%A8s-M%C3%A2con_%28FR71%29_-_2024-05-08_-_1.jpg/960px-Place_19_Mars_1962_-_Varennes-l%C3%A8s-M%C3%A2con_%28FR71%29_-_2024-05-08_-_1.jpg"},{"slug":"lac-intercommunal-saint-point-saint-point","name":"Lac Intercommunal Saint Point","city":"Saint-Point","department":"Saône-et-Loire","type":"Lac","distanceKm":18.2,"score":95,"lastWaterQuality":"Bon","thumbUrl":"https://upload.wikimedia.org/wikipedia/commons/thumb/5/5d/Lac_Saint_Point_-_Saint-Point_%28FR71%29_-_2026-03-04_-_2.jpg/960px-Lac_Saint_Point_-_Saint-Point_%28FR71%29_-_2026-03-04_-_2.jpg"},{"slug":"pont-de-vaux-rive-gauche-de-la-saone-en-aval-du-pont-de-fleurville-pont-de-vaux","name":"Pont-de-Vaux - Rive Gauche de la Saone en Aval du Pont de Fleurville","city":"Pont-de-Vaux","department":"Ain","type":"Rivière","distanceKm":24.3,"score":10,"lastWaterQuality":"Excellent"},{"slug":"malafretaz-plan-d-eau-de-la-base-de-plein-air-la-plaine-tonique-malafretaz","name":"Malafretaz - Plan d'Eau de la Base de Plein Air la Plaine Tonique","city":"Malafretaz","department":"Ain","type":"Lac","distanceKm":28.1,"score":95,"lastWaterQuality":"Excellent","thumbUrl":"https://upload.wikimedia.org/wikipedia/commons/thumb/f/fa/Tour_de_l%27Ain_2016_-_Plaine_Tonique.jpg/960px-Tour_de_l%27Ain_2016_-_Plaine_Tonique.jpg"},{"slug":"plan-d-eau-du-bordelan-villefranche-sur-saone","name":"Plan d'Eau du Bordelan","city":"Villefranche-sur-Saone","department":"Rhône","type":"Lac","distanceKm":30,"score":95,"lastWaterQuality":"Excellent","thumbUrl":"https://upload.wikimedia.org/wikipedia/commons/thumb/f/ff/Villefranche-sur-Sa%C3%B4ne_-_Plan_d%27eau_de_Bordelan_%28sept_2018%29.jpg/960px-Villefranche-sur-Sa%C3%B4ne_-_Plan_d%27eau_de_Bordelan_%28sept_2018%29.jpg"},{"slug":"plan-d-eau-du-colombier-anse","name":"Plan d'Eau du Colombier","city":"Anse","department":"Rhône","type":"Lac","distanceKm":32.2,"score":95,"lastWaterQuality":"Excellent","thumbUrl":"https://www.cc-pierresdorees.com/sites/default/files/sports/144_745_colombier-7.jpg"},{"slug":"bourg-en-bresse-plan-d-eau-du-parc-de-loisirs-de-bouvent-bourg-en-bresse","name":"Bourg en Bresse - Plan d'Eau du Parc de Loisirs de Bouvent","city":"Bourg-en-Bresse","department":"Ain","type":"Lac","distanceKm":35.6,"score":85,"lastWaterQuality":"Excellent"},{"slug":"lac-des-sapins-baignade-point-sud-cublize","name":"Lac des Sapins-Baignade Point Sud","city":"Cublize","department":"Rhône","type":"Lac","distanceKm":41.7,"score":100,"lastWaterQuality":"Bon","thumbUrl":"https://img.centrefrance.com/ndgJ1Ui17890tvEW-b964CL1ayx0S2uxRroMH6h300Y/rs:fit:657:438:1:0/bG9jYWw6Ly8vMDAvMDAvMDUvMzkvMDIvMjAwMDAwNTM5MDI0OA.webp"}]}