{"region":"Auvergne-Rhône-Alpes","code":"FRK1343052D043060","situationUpdate":"Pas de changement","name":"Plan d'Eau","insee":"43052","city":"Champagnac-le-Vieux","ueDeclarationDate":"01/01/1991","type":"Lac","lng":"3.50280419329","lat":"45.36679020874","idSite":"001575","siteDetails":{"surveillance":true,"amenities":true,"animalsAllowed":true,"showers":true,"drinkingWater":true,"wheelchairAccess":false,"toilets":true,"lifeguard":true,"seasonStart":"2025-07-05T00:00:00.000Z","seasonEnd":"2025-08-31T00:00:00.000Z","lastWaterQuality":"Excellent","lastTestDate":"2025-09-01T00:00:00.000Z"},"score":85,"images":[],"department":"Haute-Loire","slug":"plan-d-eau-champagnac-le-vieux","nearbySpots":[{"slug":"allier-la-bageasse-vieille-brioude","name":"Allier-la Bageasse","city":"Vieille-Brioude","department":"Haute-Loire","type":"Rivière","distanceKm":12.3,"score":65,"lastWaterQuality":"Bon"},{"slug":"plan-d-eau-du-vernet-la-varenne-vernet-chameane-le","name":"Plan d'Eau du Vernet la Varenne","city":"Vernet-Chameane (Le)","department":"Puy-de-Dôme","type":"Lac","distanceKm":12.7,"score":85,"lastWaterQuality":"Excellent"},{"slug":"plan-d-eau-de-la-tour-chaise-dieu-la","name":"Plan d'Eau de la Tour","city":"Chaise-Dieu (La)","department":"Haute-Loire","type":"Lac","distanceKm":16.3,"score":35,"lastWaterQuality":"Excellent","thumbUrl":"https://upload.wikimedia.org/wikipedia/commons/thumb/2/22/Moustique_mosquito_%282732269050%29.jpg/960px-Moustique_mosquito_%282732269050%29.jpg"},{"slug":"allier-rive-gauche-camping-villeneuve-d-allier","name":"Allier Rive Gauche  Camping","city":"Villeneuve-d'Allier","department":"Haute-Loire","type":"Rivière","distanceKm":19.3,"score":15,"lastWaterQuality":"Bon"},{"slug":"allier-rive-gauche-chilhac","name":"Allier Rive Gauche","city":"Chilhac","department":"Haute-Loire","type":"Rivière","distanceKm":24.2,"score":30,"lastWaterQuality":"Bon"},{"slug":"allier-pont-de-lavoute-chilhac-lavoute-chilhac","name":"Allier Pont de Lavoute Chilhac","city":"Lavoute-Chilhac","department":"Haute-Loire","type":"Rivière","distanceKm":25.5,"score":55,"lastWaterQuality":"Bon"},{"slug":"plan-d-eau-de-cunlhat-cunlhat","name":"Plan d'Eau de Cunlhat","city":"Cunlhat","department":"Puy-de-Dôme","type":"Lac","distanceKm":29,"score":-30,"lastWaterQuality":"Insuffisant"},{"slug":"allier-ile-d-amour-langeac","name":"Allier - Ile d'Amour","city":"Langeac","department":"Haute-Loire","type":"Rivière","distanceKm":30.3,"score":35,"lastWaterQuality":"Bon","thumbUrl":"https://upload.wikimedia.org/wikipedia/commons/thumb/7/7b/Pyroclastic_rock_in_Langeac_in_Auvergne_in_France.jpg/960px-Pyroclastic_rock_in_Langeac_in_Auvergne_in_France.jpg"}]}