{"region":"Normandie","code":"FRD1250412M050280","situationUpdate":"Pas de changement","name":"Saint-Lo d'Ourville Lindbergh-Plage","insee":"50412","city":"Port-Bail-sur-Mer","ueDeclarationDate":"01/01/1991","type":"Eau côtière","lng":"-1.70475981763","lat":"49.31526358518","idSite":"002145","siteDetails":{"surveillance":false,"amenities":false,"animalsAllowed":true,"showers":false,"drinkingWater":false,"wheelchairAccess":false,"toilets":false,"lifeguard":false,"seasonStart":"2025-06-15T00:00:00.000Z","seasonEnd":"2025-09-15T00:00:00.000Z","lastWaterQuality":"Excellent","lastTestDate":"2025-09-01T00:00:00.000Z"},"score":10,"images":[],"department":"Manche","slug":"saint-lo-d-ourville-lindbergh-plage-port-bail-sur-mer"}